Metadata-Version: 2.1
Name: sm2rain
Version: 0.0.1
Summary: Add a short description here!
Home-page: http://...
Author: Sebastian Hahn
Author-email: sebastian.hahn@geo.tuwien.ac.at
License: none
Platform: UNKNOWN
Classifier: Development Status :: 4 - Beta
Classifier: Programming Language :: Python
Provides-Extra: test
